human_body_prior/__init__.py
human_body_prior/body_model/__init__.py
human_body_prior/body_model/body_model.py
human_body_prior/body_model/lbs.py
human_body_prior/data/__init__.py
human_body_prior/data/dataloader.py
human_body_prior/data/prepare_data.py
human_body_prior/evaluate/__init__.py
human_body_prior/evaluate/adapt_smlify_results.py
human_body_prior/evaluate/generate_poses.py
human_body_prior/evaluate/run_testset.py
human_body_prior/mesh/__init__.py
human_body_prior/mesh/mesh_viewer.py
human_body_prior/mesh/sphere.py
human_body_prior/tools/__init__.py
human_body_prior/tools/model_loader.py
human_body_prior/tools/omni_tools.py
human_body_prior/tools/training_tools.py
human_body_prior/tools/visualization_tools.py
human_body_prior/train/__init__.py
human_body_prior/train/vposer_single_trainer.py
human_body_prior/train/vposer_smpl.py
human_body_prior/tutorials/__init__.py
human_body_prior/tutorials/sample_body_pose.py
human_body_prior-0.8.1.dist-info/LICENSE
human_body_prior-0.8.1.dist-info/METADATA
human_body_prior-0.8.1.dist-info/WHEEL
human_body_prior-0.8.1.dist-info/top_level.txt
human_body_prior-0.8.1.dist-info/RECORD
