Metadata-Version: 2.1
Name: human-body-prior
Version: 0.8.1
Summary: Variational human pose prior for human pose synthesis and estimation.
Home-page: https://github.com/nghorbani/HumanBodyPrior
Author: Nima Ghorbani
Author-email: nima.gbani@gmail.com
Maintainer: Nima Ghorbani
Maintainer-email: nima.gbani@gmail.com
License: GNU Affero General Public License, version 3
Platform: UNKNOWN
Classifier: Intended Audience :: Developers
Classifier: License :: OSI Approved :: GNU General Public License v3 (GPLv3)
Classifier: Natural Language :: English
Classifier: Operating System :: MacOS :: MacOS X
Classifier: Operating System :: POSIX
Classifier: Operating System :: POSIX :: BSD
Classifier: Operating System :: POSIX :: Linux
Classifier: Operating System :: Microsoft :: Windows
Classifier: Programming Language :: Python
Classifier: Programming Language :: Python :: 3
Classifier: Programming Language :: Python :: 3.7
Requires-Dist: torch (>=1.1.0)
Requires-Dist: tensorboardX (>=1.6)
Requires-Dist: torchgeometry (>=0.1.2)
Requires-Dist: opencv-python (>=4.1.0.25)
Requires-Dist: scikit-image (>=0.15.0)
Requires-Dist: configer (>=1.2.3)
Requires-Dist: imageio (>=2.5.0)
Requires-Dist: transforms3d (>=0.3.1)
Requires-Dist: trimesh
